helisol/__init__.py
helisol/__main__.py
helisol/config.py
helisol/earth.py
helisol/general.py
helisol/locations.py
helisol/sun.py
helisol/tables.py
helisol-0.5.3.dist-info/licenses/LICENSE
locations/global.json
tests/test_helisol.py
helisol-0.5.3.dist-info/METADATA
helisol-0.5.3.dist-info/WHEEL
helisol-0.5.3.dist-info/top_level.txt
helisol-0.5.3.dist-info/RECORD
