Metadata-Version: 2.4
Name: helisol
Version: 0.5.3
Summary: Get precise position of sun in sky (height, azimuth) at given location and time, get sunrise and sunset time, generate sundials.
Author-email: Olivier Vincent <ovinc.py@gmail.com>
License: GNU GPLv3
Project-URL: Homepage, https://github.com/ovinc/helisol
Project-URL: Documentation, https://github.com/ovinc/helisol/README.md
Project-URL: Repository, https://github.com/ovinc/helisol.git
Keywords: sun,position,azimuth,height,sunset,sunrise,noon,sundial,astronomy,angle,time
Classifier: Programming Language :: Python :: 3
Classifier: Operating System :: OS Independent
Classifier: License :: OSI Approved :: GNU General Public License v3 or later (GPLv3+)
Requires-Python: >=3.7
License-File: LICENSE
Requires-Dist: numpy
Requires-Dist: pandas
Requires-Dist: oclock
Requires-Dist: importlib-metadata
Dynamic: license-file
